bedparse/__init__.py
bedparse/bedline.py
bedparse/bedparse.py
bedparse/chrnames.py
bedparse/converters.py
bedparse-0.2.3.dist-info/LICENSE.txt
bedparse-0.2.3.dist-info/METADATA
bedparse-0.2.3.dist-info/WHEEL
bedparse-0.2.3.dist-info/entry_points.txt
bedparse-0.2.3.dist-info/top_level.txt
bedparse-0.2.3.dist-info/RECORD
