Metadata-Version: 2.1
Name: bedparse
Version: 0.2.3
Summary: A simple library and CLI tool to manipulate BED files
Home-page: https://github.com/tleonardi/bedparse
Author: Tommaso Leonardi
Author-email: tom@tleo.io
License: MIT
Platform: UNKNOWN
Classifier: Development Status :: 5 - Production/Stable
Classifier: License :: OSI Approved :: MIT License
Classifier: Programming Language :: Python :: 3.4
Classifier: Programming Language :: Python :: 3.5
Classifier: Programming Language :: Python :: 3.6
Requires-Python: >=3.4
Requires-Dist: argparse
Requires-Dist: setuptools
